Unity3dJiaochengCYuyanBianchengWang/README.md
Unity3dJiaochengCYuyanBianchengWang/__init__.py
Unity3dJiaochengCYuyanBianchengWang/__main__.py
Unity3dJiaochengCYuyanBianchengWang/file.epub
Unity3dJiaochengCYuyanBianchengWang/index.html
Unity3dJiaochengCYuyanBianchengWang/css/__init__.py
Unity3dJiaochengCYuyanBianchengWang/css/annotations.css
Unity3dJiaochengCYuyanBianchengWang/css/main.css
Unity3dJiaochengCYuyanBianchengWang/css/normalize.css
Unity3dJiaochengCYuyanBianchengWang/css/popup.css
Unity3dJiaochengCYuyanBianchengWang/font/__init__.py
Unity3dJiaochengCYuyanBianchengWang/font/fontello.eot
Unity3dJiaochengCYuyanBianchengWang/font/fontello.svg
Unity3dJiaochengCYuyanBianchengWang/font/fontello.ttf
Unity3dJiaochengCYuyanBianchengWang/font/fontello.woff
Unity3dJiaochengCYuyanBianchengWang/img/__init__.py
Unity3dJiaochengCYuyanBianchengWang/img/annotator-glyph-sprite.png
Unity3dJiaochengCYuyanBianchengWang/img/annotator-icon-sprite.png
Unity3dJiaochengCYuyanBianchengWang/img/apple-touch-icon.png
Unity3dJiaochengCYuyanBianchengWang/img/cancelfullscreen.png
Unity3dJiaochengCYuyanBianchengWang/img/close.png
Unity3dJiaochengCYuyanBianchengWang/img/fullscreen.png
Unity3dJiaochengCYuyanBianchengWang/img/loader.gif
Unity3dJiaochengCYuyanBianchengWang/img/menu-icon.png
Unity3dJiaochengCYuyanBianchengWang/img/save.png
Unity3dJiaochengCYuyanBianchengWang/img/saved.png
Unity3dJiaochengCYuyanBianchengWang/img/settings-s.png
Unity3dJiaochengCYuyanBianchengWang/img/settings.png
Unity3dJiaochengCYuyanBianchengWang/img/star.png
Unity3dJiaochengCYuyanBianchengWang/js/__init__.py
Unity3dJiaochengCYuyanBianchengWang/js/epub.js
Unity3dJiaochengCYuyanBianchengWang/js/epub.min.js
Unity3dJiaochengCYuyanBianchengWang/js/epub.min.map
Unity3dJiaochengCYuyanBianchengWang/js/hooks.min.js
Unity3dJiaochengCYuyanBianchengWang/js/hooks.min.map
Unity3dJiaochengCYuyanBianchengWang/js/reader.js
Unity3dJiaochengCYuyanBianchengWang/js/reader.js.map
Unity3dJiaochengCYuyanBianchengWang/js/reader.min.js
unity_3d_jiaocheng_c_yuyan_biancheng_wang-2024.3.5.0.dist-info/METADATA
unity_3d_jiaocheng_c_yuyan_biancheng_wang-2024.3.5.0.dist-info/WHEEL
unity_3d_jiaocheng_c_yuyan_biancheng_wang-2024.3.5.0.dist-info/entry_points.txt
unity_3d_jiaocheng_c_yuyan_biancheng_wang-2024.3.5.0.dist-info/top_level.txt
unity_3d_jiaocheng_c_yuyan_biancheng_wang-2024.3.5.0.dist-info/RECORD
